grade/__init__.py
grade/__main__.py
grade/cli/__init__.py
grade/cli/report.py
grade/cli/run.py
grade/decorators.py
grade/mixins.py
grade/pipeline/__init__.py
grade/pipeline/asserts.py
grade/pipeline/completedprocess.py
grade/pipeline/partialcredit.py
grade/pipeline/pipeline.py
grade/pipeline/run.py
grade/pipeline/write.py
grade/result.py
grade/runners.py
grade-3.0.0.dist-info/LICENSE
grade-3.0.0.dist-info/WHEEL
grade-3.0.0.dist-info/METADATA
grade-3.0.0.dist-info/RECORD
