Metadata-Version: 2.1
Name: grade
Version: 3.0.0
Summary: a package focused on autograding
Home-page: https://github.com/thoward27/grade
License: AGPL-3.0
Author: Tom
Author-email: info@tomhoward.codes
Requires-Python: >=3.6,<4.0
Classifier: License :: OSI Approved :: GNU Affero General Public License v3
Classifier: Programming Language :: Python :: 3
Classifier: Programming Language :: Python :: 3.6
Classifier: Programming Language :: Python :: 3.7
Classifier: Programming Language :: Python :: 3.8
Requires-Dist: click (>=7.0,<8.0)
Project-URL: Documentation, https://grade.readthedocs.io/en/latest/
Project-URL: Repository, https://github.com/thoward27/grade
